kaggleDownloader/__init__.py
kaggleDownloader/kaggleDownloader.py
kaggleDownloader-4.2.1.dist-info/LICENSE.txt
kaggleDownloader-4.2.1.dist-info/METADATA
kaggleDownloader-4.2.1.dist-info/WHEEL
kaggleDownloader-4.2.1.dist-info/top_level.txt
kaggleDownloader-4.2.1.dist-info/RECORD
