Metadata-Version: 2.1
Name: kaggleDownloader
Version: 4.2.1
Summary: Helps you to download the Kaggle Dataset to your Google Colab Notebook using Kaggle Dataset API link
Home-page: https://gitlab.com/antoreep_jana/kaggledownloader/tree/master
Author: Antoreep Jana
Author-email: antoreepjana@gmail.com
License: MIT
Download-URL: https://gitlab.com/antoreep_jana/kaggledownloader/-/archive/4.2.1/kaggledownloader-4.2.1.tar.gz
Keywords: Kaggle Downloader,Kaggle Dataset Downloader,dataset downloader,Google Colab,kaggle dataset download in google colab
Platform: UNKNOWN
Classifier: Development Status :: 3 - Alpha
Classifier: Intended Audience :: Developers
Classifier: Topic :: Software Development :: Build Tools
Classifier: License :: OSI Approved :: MIT License
Classifier: Programming Language :: Python :: 3
Classifier: Programming Language :: Python :: 3.4
Classifier: Programming Language :: Python :: 3.5
Classifier: Programming Language :: Python :: 3.6
